neptune_query/__init__.py
neptune_query/_internal.py
neptune_query/exceptions.py
neptune_query/experimental/__init__.py
neptune_query/filters.py
neptune_query/generated/neptune_api/__init__.py
neptune_query/generated/neptune_api/api/__init__.py
neptune_query/generated/neptune_api/api/backend/__init__.py
neptune_query/generated/neptune_api/api/backend/exchange_api_token.py
neptune_query/generated/neptune_api/api/backend/get_client_config.py
neptune_query/generated/neptune_api/api/backend/get_project.py
neptune_query/generated/neptune_api/api/ingestion/__init__.py
neptune_query/generated/neptune_api/api/ingestion/bulk_check_status.py
neptune_query/generated/neptune_api/api/ingestion/check_details.py
neptune_query/generated/neptune_api/api/ingestion/check_status.py
neptune_query/generated/neptune_api/api/ingestion/ingest.py
neptune_query/generated/neptune_api/api/retrieval/__init__.py
neptune_query/generated/neptune_api/api/retrieval/get_attributes_with_paths_filter_proto.py
neptune_query/generated/neptune_api/api/retrieval/get_multiple_float_series_values_proto.py
neptune_query/generated/neptune_api/api/retrieval/get_series_values_proto.py
neptune_query/generated/neptune_api/api/retrieval/get_timeseries_buckets_proto.py
neptune_query/generated/neptune_api/api/retrieval/query_attribute_definitions_proto.py
neptune_query/generated/neptune_api/api/retrieval/query_attribute_definitions_within_project.py
neptune_query/generated/neptune_api/api/retrieval/query_attributes_within_project_proto.py
neptune_query/generated/neptune_api/api/retrieval/search_global_leaderboard_entries_proto.py
neptune_query/generated/neptune_api/api/retrieval/search_leaderboard_entries_proto.py
neptune_query/generated/neptune_api/api/storage/__init__.py
neptune_query/generated/neptune_api/api/storage/complete_multipart_upload.py
neptune_query/generated/neptune_api/api/storage/signed_url.py
neptune_query/generated/neptune_api/api/storage/signed_url_generic.py
neptune_query-1.11.0.dist-info/METADATA
neptune_query-1.11.0.dist-info/WHEEL
neptune_query-1.11.0.dist-info/licenses/LICENSE
neptune_query-1.11.0.dist-info/RECORD
